odoo10_addon_account_banking_sepa_credit_transfer-10.0.1.1.0-py2.7-nspkg.pth
odoo/addons/account_banking_sepa_credit_transfer/README.rst
odoo/addons/account_banking_sepa_credit_transfer/__init__.py
odoo/addons/account_banking_sepa_credit_transfer/__manifest__.py
odoo/addons/account_banking_sepa_credit_transfer/post_install.py
odoo/addons/account_banking_sepa_credit_transfer/data/account_payment_method.xml
odoo/addons/account_banking_sepa_credit_transfer/data/pain.001.001.02.xsd
odoo/addons/account_banking_sepa_credit_transfer/data/pain.001.001.03.xsd
odoo/addons/account_banking_sepa_credit_transfer/data/pain.001.001.04.xsd
odoo/addons/account_banking_sepa_credit_transfer/data/pain.001.001.05.xsd
odoo/addons/account_banking_sepa_credit_transfer/data/pain.001.003.03.xsd
odoo/addons/account_banking_sepa_credit_transfer/demo/sepa_credit_transfer_demo.xml
odoo/addons/account_banking_sepa_credit_transfer/i18n/account_banking_sepa_credit_transfer.pot
odoo/addons/account_banking_sepa_credit_transfer/i18n/da_DK.po
odoo/addons/account_banking_sepa_credit_transfer/i18n/de.po
odoo/addons/account_banking_sepa_credit_transfer/i18n/es.po
odoo/addons/account_banking_sepa_credit_transfer/i18n/fr.po
odoo/addons/account_banking_sepa_credit_transfer/i18n/hr.po
odoo/addons/account_banking_sepa_credit_transfer/i18n/nb_NO.po
odoo/addons/account_banking_sepa_credit_transfer/i18n/nl.po
odoo/addons/account_banking_sepa_credit_transfer/i18n/pt_BR.po
odoo/addons/account_banking_sepa_credit_transfer/i18n/sl.po
odoo/addons/account_banking_sepa_credit_transfer/models/__init__.py
odoo/addons/account_banking_sepa_credit_transfer/models/account_payment_line.py
odoo/addons/account_banking_sepa_credit_transfer/models/account_payment_method.py
odoo/addons/account_banking_sepa_credit_transfer/models/account_payment_order.py
odoo/addons/account_banking_sepa_credit_transfer/static/description/icon.png
odoo/addons/account_banking_sepa_credit_transfer/static/description/icon.svg
odoo10_addon_account_banking_sepa_credit_transfer-10.0.1.1.0.dist-info/METADATA
odoo10_addon_account_banking_sepa_credit_transfer-10.0.1.1.0.dist-info/RECORD
odoo10_addon_account_banking_sepa_credit_transfer-10.0.1.1.0.dist-info/WHEEL
odoo10_addon_account_banking_sepa_credit_transfer-10.0.1.1.0.dist-info/namespace_packages.txt
odoo10_addon_account_banking_sepa_credit_transfer-10.0.1.1.0.dist-info/top_level.txt
